{
  "entrypoints": {
    "form": {
      "js": [
        "build/runtime.d41d8cd9.js",
        "build/vendors~dfe491aa.b248167b.js",
        "build/vendors~9072dba1.0eb78412.js",
        "build/form.b355246a.js"
      ],
      "css": [
        "build/form.6e0904a2.css"
      ]
    },
    "core": {
      "js": [
        "build/runtime.d41d8cd9.js",
        "build/vendors~dfe491aa.b248167b.js",
        "build/vendors~1aeabec8.6a716a5e.js",
        "build/core.f40ff06f.js"
      ],
      "css": [
        "build/vendors~1aeabec8.35d7db45.css",
        "build/core.f91f085e.css"
      ]
    },
    "timetable": {
      "js": [
        "build/runtime.d41d8cd9.js",
        "build/vendors~dfe491aa.b248167b.js",
        "build/vendors~9072dba1.0eb78412.js",
        "build/timetable.f3bee5e0.js"
      ],
      "css": [
        "build/timetable.20a7221d.css"
      ]
    },
    "notificationTray": {
      "js": [
        "build/runtime.d41d8cd9.js",
        "build/vendors~dfe491aa.b248167b.js",
        "build/vendors~9072dba1.0eb78412.js",
        "build/notificationTray.bca3dbac.js"
      ]
    }
  }
}